{
    "base_dirs": [
        {
            "dir": "../shared_task_code",
            "base_in_zip": "python/shared_task_code"
        },
        {
            "dir": "../.venv/Lib/site-packages",
            "base_in_zip": "python",
            "exclude_dev_deps": true
        }
    ],
    "excludes": [
        "test_utils",
        "aws_messaging_glue",
        "dlq_recorder",
        "package_lambda.py",
        "docutils",
        "jmespath",
        "python-dateutil",
        "s3transfer",
        "six",
        "pip",
        "setuptools"
    ]
}